{
    "skills": [
        {
            "id": "1",
            "source": "./img/loujo.jpg",
            "title": "Software Developer Intern",
            "dates": "September 2025 - Present",
            "description": "Designed and implemented a React application for a children educational platform. Conducted research to figure out the best suited features for an educational app.",
            "skills": "React, Front-end Programming, Research"
        },
        {
            "id": "2",
            "source": "./img/map.png",
            "title": "Front-End Programmer",
            "dates": "July 2025 - Present",
            "description": "Designed and implemented a Java-based mapping application to visualize geospatial data points on interactive maps.",
            "skills": "Java Swing, API Integration, GeoTools, Dependency Management"
        },
        {
            "id": "3",
            "source": "./img/depaul.jpg",
            "title": "Supplemental Instruction Leader",
            "dates": "March 2025 - June 2025",
            "description": "Facilitated 2-3 weekly collaborative review sessions for Data Structures students, reviewing core concepts like linked-lists, stacks, queues, and trees through guided practice.",
            "skills": "Data Structures, Algorithms, Teaching and Collaboration"
        }
    ],

    "projects": [

        {
            "id": "1",
            "source": "./img/website.jpeg",
            "title": "Portfolio Website",
            "description": "I designed and implemented a single-page React application to highlight professional experience and personal projects.",
            "skills": "React, CSS",
            "link": "https://github.com/amyfan7/portfolio-react"
        }
    ]
}